pyselector/__init__.py
pyselector/colors.py
pyselector/constants.py
pyselector/exc.py
pyselector/extract.py
pyselector/helpers.py
pyselector/interfaces.py
pyselector/key_manager.py
pyselector/logger.py
pyselector/markup.py
pyselector/selector.py
pyselector/menus/__init__.py
pyselector/menus/dmenu.py
pyselector/menus/fzf.py
pyselector/menus/interface.py
pyselector/menus/rofi.py
pyselector/menus/rofi_beta.py
pyselector-0.0.41.dist-info/METADATA
pyselector-0.0.41.dist-info/WHEEL
pyselector-0.0.41.dist-info/licenses/LICENSE.txt
pyselector-0.0.41.dist-info/RECORD
