Metadata-Version: 2.3
Name: pyselector
Version: 0.0.41
Summary: WIP
Project-URL: Documentation, https://github.com/haaag/pyselector#readme
Project-URL: Issues, https://github.com/haaag/pyselector/issues
Project-URL: Source, https://github.com/haaag/pyselector
Author-email: haaag <git.haaag@gmail.com>
License: MIT License
License-File: LICENSE.txt
Keywords: cli,dmenu,fzf,menu,rofi,utility
Requires-Python: >=3.7
Requires-Dist: pillow==10.4.0
Requires-Dist: python-xlib==0.33
Provides-Extra: dev
Requires-Dist: mypy==1.0.1; extra == 'dev'
Requires-Dist: ruff==0.0.257; extra == 'dev'
Provides-Extra: test
Requires-Dist: coverage[toml]<8.0,>=6.5; extra == 'test'
Requires-Dist: pytest<8.0.0,>=7.1.3; extra == 'test'
